{
 "eventId": "26a1bf9e-abe3-4048-8256-ec7f479ba8d7",
 "eventType": "paymentNRT",
 "processTime": "2023-10-06T20:21:32.983197Z",
 "responseBody": "paymentNRT",
 "responseHeaders": {
  "Access-Control-Allow-Headers": [
   "Origin, X-Requested-With, Content-Type, Content-Length, Accept"
  ],
  "Access-Control-Allow-Origin": [
   "*"
  ],
  "Cache-Control": [
   "no-store, no-cache, must-revalidate, proxy-revalidate, max-age=0"
  ],
  "Connection": [
   "keep-alive"
  ],
  "Content-Type": [
   "text/plain;charset=utf-8"
  ],
  "Date": [
   "Fri, 06 Oct 2023 20:21:32 GMT"
  ],
  "Server": [
   "webserver"
  ],
  "X-Content-Type-Options": [
   "nosniff"
  ],
  "X-Xss-Protection": [
   "1; mode=block"
  ]
 },
 "responseStatus": "204 No Content",
 "transactionId": "649b5a90-4b6e-4370-84f9-aaa0fd679896"
}