{
 "eventId": "4a702d48-f8e0-4030-b5a3-dc4f4132c446",
 "eventType": "paymentNRT",
 "processTime": "2023-10-06T20:21:33.535513Z",
 "responseBody": "paymentNRT",
 "responseHeaders": {
  "Access-Control-Allow-Headers": [
   "Origin, X-Requested-With, Content-Type, Content-Length, Accept"
  ],
  "Access-Control-Allow-Origin": [
   "*"
  ],
  "Cache-Control": [
   "no-store, no-cache, must-revalidate, proxy-revalidate, max-age=0"
  ],
  "Connection": [
   "keep-alive"
  ],
  "Content-Type": [
   "text/plain;charset=utf-8"
  ],
  "Date": [
   "Fri, 06 Oct 2023 20:21:33 GMT"
  ],
  "Server": [
   "webserver"
  ],
  "X-Content-Type-Options": [
   "nosniff"
  ],
  "X-Xss-Protection": [
   "1; mode=block"
  ]
 },
 "responseStatus": "204 No Content",
 "transactionId": "63ea3789-029c-4c7b-be4c-b21c258fd5a6"
}