{
 "eventId": "64cc114a-6190-4371-b495-e095e6afc263",
 "eventType": "paymentNRT",
 "processTime": "2023-10-06T20:21:20.0989Z",
 "responseBody": "paymentNRT",
 "responseHeaders": {
  "Access-Control-Allow-Headers": [
   "Origin, X-Requested-With, Content-Type, Content-Length, Accept"
  ],
  "Access-Control-Allow-Origin": [
   "*"
  ],
  "Cache-Control": [
   "no-store, no-cache, must-revalidate, proxy-revalidate, max-age=0"
  ],
  "Connection": [
   "keep-alive"
  ],
  "Content-Type": [
   "text/plain;charset=utf-8"
  ],
  "Date": [
   "Fri, 06 Oct 2023 20:21:20 GMT"
  ],
  "Server": [
   "webserver"
  ],
  "X-Content-Type-Options": [
   "nosniff"
  ],
  "X-Xss-Protection": [
   "1; mode=block"
  ]
 },
 "responseStatus": "204 No Content",
 "transactionId": "6683f7c6-6fb1-4f55-b309-8d32e1d82e73"
}