{
 "eventId": "ab4286df-6281-434f-967c-f3a125503c5e",
 "eventType": "paymentNRT",
 "processTime": "2023-10-06T20:21:40.749051Z",
 "responseBody": "paymentNRT",
 "responseHeaders": {
  "Access-Control-Allow-Headers": [
   "Origin, X-Requested-With, Content-Type, Content-Length, Accept"
  ],
  "Access-Control-Allow-Origin": [
   "*"
  ],
  "Cache-Control": [
   "no-store, no-cache, must-revalidate, proxy-revalidate, max-age=0"
  ],
  "Connection": [
   "keep-alive"
  ],
  "Content-Type": [
   "text/plain;charset=utf-8"
  ],
  "Date": [
   "Fri, 06 Oct 2023 20:21:40 GMT"
  ],
  "Server": [
   "webserver"
  ],
  "X-Content-Type-Options": [
   "nosniff"
  ],
  "X-Xss-Protection": [
   "1; mode=block"
  ]
 },
 "responseStatus": "204 No Content",
 "transactionId": "c389df02-9c92-4bcb-9655-133615daa029"
}